spexm8p/__init__.py
spexm8p/builder.py
spexm8p/chex.py
spexm8p/parser.py
spexm8p/spex.py
spexm8p/token.py
spexm8p-0.0.4.dist-info/LICENSE
spexm8p-0.0.4.dist-info/METADATA
spexm8p-0.0.4.dist-info/WHEEL
spexm8p-0.0.4.dist-info/top_level.txt
spexm8p-0.0.4.dist-info/RECORD
