Metadata-Version: 2.1
Name: spexm8p
Version: 0.0.4
Summary: spexm8p: String pattern expressions prototype that can be logically operated
Home-page: https://github.com/j5c8k6m8/spex-m8p-py
Author: j5c8k6m8
Author-email: j5c8k6m8@gmail.com
License: UNKNOWN
Platform: UNKNOWN
License-File: LICENSE
